odoo10_addon_web_environment_ribbon-10.0.1.0.0-py2.7-nspkg.pth
odoo/addons/web_environment_ribbon/__manifest__.py
odoo/addons/web_environment_ribbon/__init__.py
odoo/addons/web_environment_ribbon/README.rst
odoo/addons/web_environment_ribbon/view/base_view.xml
odoo/addons/web_environment_ribbon/data/ribbon_data.xml
odoo/addons/web_environment_ribbon/static/description/screenshot.png
odoo/addons/web_environment_ribbon/static/description/icon.png
odoo/addons/web_environment_ribbon/static/src/js/ribbon.js
odoo/addons/web_environment_ribbon/static/src/css/ribbon.css
odoo10_addon_web_environment_ribbon-10.0.1.0.0.dist-info/top_level.txt
odoo10_addon_web_environment_ribbon-10.0.1.0.0.dist-info/WHEEL
odoo10_addon_web_environment_ribbon-10.0.1.0.0.dist-info/RECORD
odoo10_addon_web_environment_ribbon-10.0.1.0.0.dist-info/metadata.json
odoo10_addon_web_environment_ribbon-10.0.1.0.0.dist-info/DESCRIPTION.rst
odoo10_addon_web_environment_ribbon-10.0.1.0.0.dist-info/METADATA
odoo10_addon_web_environment_ribbon-10.0.1.0.0.dist-info/namespace_packages.txt
